<?xml version="1.0" encoding="utf-8"?>
<t2ti-orm-mapping>
  <class name="CteDutoviarioVO" table="cte_dutoviario" >

    <id name="Id" column="ID">
      <generator class="sequence">
        <param name="sequence">cte_dutoviario</param>
      </generator>
    </id>

    <property name="IdCteCabecalho" column="ID_CTE_CABECALHO" caption="Id Cte Cabecalho" width="80" type="Integer" />
    <property name="ValorTarifa" column="VALOR_TARIFA" caption="Valor Tarifa" width="168" type="FMTBcdField" />
    <property name="DataInicio" column="DATA_INICIO" caption="Data Inicio" width="80" type="Date" />
    <property name="DataFim" column="DATA_FIM" caption="Data Fim" width="80" type="Date" />

  </class>
</t2ti-orm-mapping>
